neurodsp/__init__.py
neurodsp/version.py
neurodsp/aperiodic/__init__.py
neurodsp/aperiodic/autocorr.py
neurodsp/aperiodic/conversions.py
neurodsp/aperiodic/dfa.py
neurodsp/aperiodic/irasa.py
neurodsp/burst/__init__.py
neurodsp/burst/dualthresh.py
neurodsp/burst/utils.py
neurodsp/filt/__init__.py
neurodsp/filt/checks.py
neurodsp/filt/filter.py
neurodsp/filt/fir.py
neurodsp/filt/iir.py
neurodsp/filt/utils.py
neurodsp/plts/__init__.py
neurodsp/plts/filt.py
neurodsp/plts/rhythm.py
neurodsp/plts/settings.py
neurodsp/plts/spectral.py
neurodsp/plts/style.py
neurodsp/plts/time_series.py
neurodsp/plts/timefrequency.py
neurodsp/plts/utils.py
neurodsp/rhythm/__init__.py
neurodsp/rhythm/lc.py
neurodsp/rhythm/swm.py
neurodsp/sim/__init__.py
neurodsp/sim/aperiodic.py
neurodsp/sim/combined.py
neurodsp/sim/cycles.py
neurodsp/sim/info.py
neurodsp/sim/periodic.py
neurodsp/sim/transients.py
neurodsp/sim/utils.py
neurodsp/spectral/__init__.py
neurodsp/spectral/checks.py
neurodsp/spectral/measures.py
neurodsp/spectral/power.py
neurodsp/spectral/utils.py
neurodsp/spectral/variance.py
neurodsp/tests/__init__.py
neurodsp/tests/conftest.py
neurodsp/tests/settings.py
neurodsp/tests/tutils.py
neurodsp/tests/burst/__init__.py
neurodsp/tests/burst/test_dualthresh.py
neurodsp/tests/burst/test_utils.py
neurodsp/tests/filt/__init__.py
neurodsp/tests/filt/test_checks.py
neurodsp/tests/filt/test_filter.py
neurodsp/tests/filt/test_fir.py
neurodsp/tests/filt/test_iir.py
neurodsp/tests/filt/test_utils.py
neurodsp/tests/plts/__init__.py
neurodsp/tests/plts/test_filt.py
neurodsp/tests/plts/test_rhythm.py
neurodsp/tests/plts/test_spectral.py
neurodsp/tests/plts/test_style.py
neurodsp/tests/plts/test_time_series.py
neurodsp/tests/plts/test_timefrequency.py
neurodsp/tests/plts/test_utils.py
neurodsp/tests/rhythm/__init__.py
neurodsp/tests/rhythm/test_lc.py
neurodsp/tests/rhythm/test_swm.py
neurodsp/tests/sim/__init__.py
neurodsp/tests/sim/test_aperiodic.py
neurodsp/tests/sim/test_combined.py
neurodsp-2.2.1.dist-info/LICENSE
neurodsp-2.2.1.dist-info/METADATA
neurodsp-2.2.1.dist-info/WHEEL
neurodsp-2.2.1.dist-info/top_level.txt
neurodsp-2.2.1.dist-info/RECORD
