Metadata-Version: 2.1
Name: neurodsp
Version: 2.2.1
Summary: Digital signal processing for neural time series.
Home-page: https://github.com/neurodsp-tools/neurodsp
Download-URL: https://github.com/neurodsp-tools/neurodsp/releases
Author: The Voytek Lab
Author-email: voyteklab@gmail.com
Maintainer: Thomas Donoghue
Maintainer-email: tdonoghue.research@gmail.com
License: Apache License, 2.0
Project-URL: Documentation, https://neurodsp-tools.github.io/
Project-URL: Bug Reports, https://github.com/neurodsp-tools/neurodsp/issues
Project-URL: Source, https://github.com/neurodsp-tools/neurodsp
Keywords: neuroscience,neural oscillations,time series analysis,local field potentials,spectral analysis,time frequency analysis,electrophysiology
Platform: any
Classifier: Development Status :: 5 - Production/Stable
Classifier: Intended Audience :: Science/Research
Classifier: Topic :: Scientific/Engineering
Classifier: License :: OSI Approved :: Apache Software License
Classifier: Operating System :: Microsoft :: Windows
Classifier: Operating System :: MacOS
Classifier: Operating System :: POSIX
Classifier: Operating System :: Unix
Classifier: Programming Language :: Python
Classifier: Programming Language :: Python :: 3.6
Classifier: Programming Language :: Python :: 3.7
Classifier: Programming Language :: Python :: 3.8
Classifier: Programming Language :: Python :: 3.9
Classifier: Programming Language :: Python :: 3.10
Requires-Python: >=3.6
License-File: LICENSE
Requires-Dist: numpy
Requires-Dist: scipy
Requires-Dist: matplotlib
